agent_factory/__init__.py
agent_factory/_console_entry.py
agent_factory/_version.py
agent_factory/py.typed
agent_factory/console/__init__.py
agent_factory/console/__main__.py
agent_factory/console/commands.py
agent_factory/console/core/__init__.py
agent_factory/console/core/agent_service.py
agent_factory/console/core/config.py
agent_factory/console/core/message_service.py
agent_factory/console/core/session_manager.py
agent_factory/console/domain/__init__.py
agent_factory/console/domain/models.py
agent_factory/console/domain/strategies.py
agent_factory/console/domain/processors/__init__.py
agent_factory/console/domain/processors/json_formatter.py
agent_factory/console/infrastructure/config/__init__.py
agent_factory/console/infrastructure/config/history_config.py
agent_factory/console/infrastructure/health/__init__.py
agent_factory/console/infrastructure/health/mcp_status.py
agent_factory/console/infrastructure/logging/__init__.py
agent_factory/console/infrastructure/logging/manager.py
agent_factory/console/ui/console_app.py
agent_factory/console/ui/styles.tcss
agent_factory/console/ui/widgets.py
agent_factory/console/ui/components/agent_components.py
agent_factory/console/ui/components/chat_components.py
agent_factory/core/__init__.py
agent_factory/core/config.py
agent_factory/core/factory.py
agent_factory/core/registry.py
agent_factory/core/utils.py
agent_factory/mcp_server/__init__.py
agent_factory/mcp_server/config.py
agent_factory/mcp_server/provider.py
agent_factory/mcp_server/auth/__init__.py
agent_factory/mcp_server/auth/app_credential_cache.py
agent_factory/mcp_server/auth/azure_credential_factory.py
agent_factory/mcp_server/auth/cert_credential.py
agent_factory/mcp_server/auth/obo_auth_filter.py
agent_factory/mcp_server/auth/obo_credential_cache.py
agent_factory/mcp_server/auth/s2s_auth.py
agent_factory/mcp_server/auth/token_parser.py
agent_factory/service/__init__.py
agent_factory/service/config.py
agent_factory/service/executor.py
semantic_kernel_agent_factory-0.0.12.dist-info/licenses/LICENSE
semantic_kernel_agent_factory-0.0.12.dist-info/METADATA
semantic_kernel_agent_factory-0.0.12.dist-info/WHEEL
semantic_kernel_agent_factory-0.0.12.dist-info/entry_points.txt
semantic_kernel_agent_factory-0.0.12.dist-info/top_level.txt
semantic_kernel_agent_factory-0.0.12.dist-info/RECORD
