Metadata-Version: 2.4
Name: semantic-kernel-agent-factory
Version: 0.0.12
Summary: SDK for creating and managing OpenAI agents with MCP server integration
Author-email: Jiahao Zhu <jiahzhu@outlook.com>
License: MIT
Project-URL: Repository, https://github.com/jhzhu89/semantic-kernel-agent-factory
Project-URL: Issues, https://github.com/jhzhu89/semantic-kernel-agent-factory/issues
Project-URL: Documentation, https://github.com/jhzhu89/semantic-kernel-agent-factory/tree/main/docs
Keywords: semantic-kernel,agent,mcp,server,factory,sdk,service,streamable_http,http
Classifier: Development Status :: 4 - Beta
Classifier: Intended Audience :: Developers
Classifier: License :: OSI Approved :: MIT License
Classifier: Operating System :: OS Independent
Classifier: Programming Language :: Python :: 3
Classifier: Programming Language :: Python :: 3.11
Classifier: Programming Language :: Python :: 3.12
Classifier: Topic :: Software Development :: Libraries :: Python Modules
Classifier: Topic :: Scientific/Engineering :: Artificial Intelligence
Requires-Python: >=3.11
License-File: LICENSE
Requires-Dist: mcp>=1.16.0
Requires-Dist: semantic-kernel>=1.37.0
Requires-Dist: pydantic>=2.11.4
Requires-Dist: pydantic-settings>=2.9.1
Requires-Dist: python-dotenv>=1.1.0
Requires-Dist: typing-extensions>=4.13.2
Requires-Dist: aiocache>=0.12.3
Requires-Dist: azure-identity>=1.19.0
Requires-Dist: PyJWT>=2.9.0
Requires-Dist: cryptography>=43.0.0
Requires-Dist: httpx>=0.28.1
Requires-Dist: PyYAML>=6.0.2
Requires-Dist: opentelemetry-api>=1.35.0
Requires-Dist: opentelemetry-sdk>=1.35.0
Requires-Dist: opentelemetry-semantic-conventions>=0.56b0
Requires-Dist: opentelemetry-exporter-otlp-proto-grpc>=1.35.0
Requires-Dist: opentelemetry-exporter-otlp-proto-http>=1.35.0
Provides-Extra: console
Requires-Dist: click>=8.2.1; extra == "console"
Requires-Dist: textual>=0.85.0; extra == "console"
Requires-Dist: anyio>=4.9.0; extra == "console"
Provides-Extra: service
Requires-Dist: a2a-sdk>=0.3.9; extra == "service"
Requires-Dist: starlette>=0.46.2; extra == "service"
Provides-Extra: dev
Requires-Dist: pytest>=7.0.0; extra == "dev"
Requires-Dist: pytest-asyncio>=0.21.0; extra == "dev"
Requires-Dist: pytest-cov>=4.0.0; extra == "dev"
Requires-Dist: pytest-mock>=3.10.0; extra == "dev"
Requires-Dist: black>=25.1.0; extra == "dev"
Requires-Dist: isort>=5.12.0; extra == "dev"
Requires-Dist: ruff>=0.1.0; extra == "dev"
Requires-Dist: flake8>=7.2.0; extra == "dev"
Requires-Dist: mypy>=1.16.0; extra == "dev"
Requires-Dist: types-PyYAML>=6.0.12.20250516; extra == "dev"
Requires-Dist: types-click>=7.1.0; extra == "dev"
Requires-Dist: pre-commit>=3.0.0; extra == "dev"
Requires-Dist: build>=1.0.0; extra == "dev"
Requires-Dist: twine>=4.0.0; extra == "dev"
Provides-Extra: dev-all
Requires-Dist: semantic-kernel-agent-factory[dev]; extra == "dev-all"
Requires-Dist: semantic-kernel-agent-factory[console]; extra == "dev-all"
Requires-Dist: semantic-kernel-agent-factory[service]; extra == "dev-all"
Provides-Extra: all
Requires-Dist: semantic-kernel-agent-factory[console]; extra == "all"
Requires-Dist: semantic-kernel-agent-factory[service]; extra == "all"
Provides-Extra: docs
Requires-Dist: sphinx>=7.1.0; extra == "docs"
Requires-Dist: sphinx-rtd-theme>=2.0.0; extra == "docs"
Requires-Dist: myst-parser>=2.0.0; extra == "docs"
Requires-Dist: sphinx-autodoc-typehints>=1.24.0; extra == "docs"
Dynamic: license-file
